LookerDF/LookerDF.py
LookerDF/__init__.py
LookerDF-1.0.1.dist-info/METADATA
LookerDF-1.0.1.dist-info/WHEEL
LookerDF-1.0.1.dist-info/top_level.txt
LookerDF-1.0.1.dist-info/RECORD
