Metadata-Version: 2.1
Name: LookerDF
Version: 1.0.1
Summary: Simple get data from Looker API into Pandas dataframe
Author: Pongsakorn Nimphaya
Requires-Python: >=3.6
